src/__init__.py
src/server.py
src/config/__init__.py
src/config/constants.py
src/config/settings.py
src/core/__init__.py
src/core/exceptions.py
src/core/validation.py
src/services/__init__.py
src/services/gemini_client.py
src/services/image_service.py
src/services/prompt_enhancer.py
src/tools/__init__.py
src/tools/batch_generate.py
src/tools/generate_image.py
ultimate_gemini_mcp-3.0.15.dist-info/METADATA
ultimate_gemini_mcp-3.0.15.dist-info/WHEEL
ultimate_gemini_mcp-3.0.15.dist-info/entry_points.txt
ultimate_gemini_mcp-3.0.15.dist-info/licenses/LICENSE
ultimate_gemini_mcp-3.0.15.dist-info/RECORD
