Metadata-Version: 2.4
Name: ultimate-gemini-mcp
Version: 3.0.15
Summary: Gemini 3 Pro Image MCP server with advanced features: high-resolution output (1K-4K), reference images (up to 14), Google Search grounding, and thinking mode
Project-URL: Homepage, https://github.com/anand-92/ultimate-image-gen-mcp
Project-URL: Repository, https://github.com/anand-92/ultimate-image-gen-mcp
Project-URL: Issues, https://github.com/anand-92/ultimate-image-gen-mcp/issues
Project-URL: Documentation, https://github.com/anand-92/ultimate-image-gen-mcp/blob/main/README.md
Author-email: Ultimate Gemini MCP <noreply@example.com>
License: MIT
License-File: LICENSE
Keywords: ai,claude,fastmcp,gemini,gemini-3-pro-image,google-ai,image-generation,mcp
Classifier: Development Status :: 4 - Beta
Classifier: Intended Audience :: Developers
Classifier: License :: OSI Approved :: MIT License
Classifier: Programming Language :: Python :: 3
Classifier: Programming Language :: Python :: 3.11
Classifier: Programming Language :: Python :: 3.12
Classifier: Topic :: Scientific/Engineering :: Artificial Intelligence
Classifier: Topic :: Software Development :: Libraries :: Python Modules
Requires-Python: >=3.11
Requires-Dist: fastmcp>=2.11.0
Requires-Dist: google-genai>=1.52.0
Requires-Dist: pillow>=10.4.0
Requires-Dist: pydantic-settings>=2.0.0
Requires-Dist: pydantic>=2.0.0
Provides-Extra: dev
Requires-Dist: mypy>=1.8.0; extra == 'dev'
Requires-Dist: pytest-asyncio>=0.24.0; extra == 'dev'
Requires-Dist: pytest-cov>=6.0.0; extra == 'dev'
Requires-Dist: pytest>=8.0.0; extra == 'dev'
Requires-Dist: ruff>=0.8.0; extra == 'dev'
